{
  "vars": [
  ],
  "includes": [
  ],
  "states": {

    "raid-battle": {
      "name": "Raid - Battle (Override)",
      "includes": [
        "_raid_battle-auto",
        "_raid-battle-message",
        "_raid-to_results",
        "_common-no_op"
      ]
    },

    "_raid_battle-auto":{
      "name": "Raid Battle - Auto (Override)",
      "statements": [
        {
          "condition": {
            "is": "SCREEN",
            "value": "game-battle",
            "and": [
              {
                "is": "SCREEN",
                "value": "game-battle-auto_off",
                "or" : [
                  {
                    "is":"SCREEN",
                    "value": "game-battle-repeat"
                  }
                ]
              },
              {
                "is": "SCREEN",
                "value": "battle-unit-1_ready"
              }
            ]
          },
          "actions": [
            {
              "type": "INFO",
              "value": "Breaking"
            },
            {
              "type": "SWIPE_RIGHT",
              "value": "battle-unit_1"
            },
            {
              "type": "WAIT",
              "value": "200"
            },
            {
              "type": "SLOW_UP",
              "value": "battle-skill-top-slider",
              "count": "7"
            },
            {
              "type": "TAP",
              "value": "battle-skill-top-5"
            },
            {
              "type": "WAIT",
              "value": "200"
            },
            {
              "type": "TAP",
              "value": "battle-unit_1"
            },
            {
              "type": "WAIT",
              "value": "400"
            },
            {
              "type": "SET",
              "value": "0",
              "var": "setup"
            },
            {
              "type": "REPEAT",
              "value": ""
            }
          ]
        },{
          "condition": {
            "is": "SCREEN",
            "value": "game-battle",
            "and": [
              {
                "is": "SCREEN",
                "value": "game-battle-auto_off",
                "or" : [
                  {
                    "is":"SCREEN",
                    "value": "game-battle-repeat"
                  }
                ]
              },
              {
                "is": "SCREEN",
                "value": "battle-unit-2_ready"
              }
            ]
          },
          "actions": [
            {
              "type": "INFO",
              "value": "Stealing"
            },
            {
              "type": "SWIPE_RIGHT",
              "value": "battle-unit_2"
            },
            {
              "type": "WAIT",
              "value": "200"
            },
            {
              "type": "TAP",
              "value": "battle-skill-top-2"
            },
            {
              "type": "WAIT",
              "value": "200"
            },
            {
              "type": "TAP",
              "value": "battle-unit_2"
            },
            {
              "type": "WAIT",
              "value": "400"
            },
            {
              "type": "SET",
              "value": "0",
              "var": "setup"
            },
            {
              "type": "REPEAT",
              "value": ""
            }
          ]
        },
        {
          "condition": {
            "is": "SCREEN",
            "value": "game-battle",
            "and": [
              {
                "is": "SCREEN",
                "value": "game-battle-auto_off",
                "or" : [
                  {
                    "is":"SCREEN",
                    "value": "game-battle-repeat"
                  }
                ]
              },
              {
                "is": "SCREEN",
                "value": "battle-unit-0_ready"
              },
              {
                "not": "SCREEN",
                "value": "battle-unit-0_ability"
              }
            ]
          },
          "actions": [
            {
              "type": "INFO",
              "value": "Nuking"
            },
            {
              "type": "SWIPE_RIGHT",
              "value": "battle-unit_0"
            },
            {
              "type": "WAIT",
              "value": "200"
            },
            {
              "type": "SLOW_UP",
              "value": "battle-skill-top-slider",
              "count": "7"
            },
            {
              "type": "TAP",
              "value": "battle-skill-top-5"
            },
            {
              "type": "WAIT",
              "value": "500"
            },
            {
              "type": "REPEAT",
              "value": ""
            }
          ]
        },


        {
          "condition": {
            "is": "SCREEN",
            "value": "game-battle",
            "and": [
              {
                "is": "SCREEN",
                "value": "game-battle-auto_off",
                "or" : [
                  {
                    "is":"SCREEN",
                    "value": "game-battle-repeat"
                  }
                ]
              },
              {
                "is": "SCREEN",
                "value": "battle-unit-3_ready"
              },
              {
                "not": "SCREEN",
                "value": "battle-unit-3_magic"
              }
            ]
          },
          "actions": [
            {
              "type": "INFO",
              "value": "Rinoa"
            },
            {
              "type": "SWIPE_RIGHT",
              "value": "battle-unit_3"
            },
            {
              "type": "WAIT",
              "value": "200"
            },
            {
              "type": "SLOW_UP",
              "value": "battle-skill-top-slider",
              "count": "6"
            },
            {
              "type": "TAP",
              "value": "battle-skill-top-2"
            },
            {
              "type": "WAIT",
              "value": "500"
            },
            {
              "type": "SLOW_DOWN",
              "value": "battle-skill-top-slider",
              "count": "3"
            },
            {
              "type": "TAP",
              "value": "battle-skill-top-0",
              "count": "3"
            },
            {
              "type": "WAIT",
              "value": "500"
            },
            {
              "type": "REPEAT",
              "value": ""
            }
          ]
        },

        {
          "condition": {
            "is": "SCREEN",
            "value": "game-battle",
            "and": [
              {
                "is": "SCREEN",
                "value": "game-battle-auto_off",
                "or" : [
                  {
                    "is":"SCREEN",
                    "value": "game-battle-repeat"
                  }
                ]
              },
              {
                "is": "SCREEN",
                "value": "battle-unit-4_ready"
              },
              {
                "not": "SCREEN",
                "value": "battle-unit-4_ability"
              }
            ]
          },
          "actions": [
            {
              "type": "INFO",
              "value": "Adam J"
            },
            {
              "type": "SWIPE_RIGHT",
              "value": "battle-unit_4"
            },
            {
              "type": "WAIT",
              "value": "200"
            },
            {
              "type": "SLOW_UP",
              "value": "battle-skill-top-slider",
              "count": "6"
            },
            {
              "type": "TAP",
              "value": "battle-skill-top-5"
            },
            {
              "type": "WAIT",
              "value": "500"
            },
            {
              "type": "REPEAT",
              "value": ""
            }
          ]
        },

        {
          "condition": {
            "is": "SCREEN",
            "value": "game-battle",
            "and": [
              {
                "is": "SCREEN",
                "value": "game-battle-auto_off",
                "or" : [
                  {
                    "is":"SCREEN",
                    "value": "game-battle-repeat"
                  }
                ]
              },
              {
                "is": "SCREEN",
                "value": "battle-unit-0_ready"
              },
              {
                "is": "SCREEN",
                "value": "battle-unit-0_ability"
              },
              {
                "is": "SCREEN",
                "value": "battle-unit-3_ready"
              },
              {
                "is": "SCREEN",
                "value": "battle-unit-3_magic"
              },
              {
                "is": "SCREEN",
                "value": "battle-unit-4_ready"
              },
              {
                "is": "SCREEN",
                "value": "battle-unit-4_ability"
              }
            ]
          },
          "actions": [
            {
              "type": "INFO",
              "value": "Attack"
            },
            {
              "type": "TAP",
              "value": "battle-unit_0"
            },
            {
              "type": "TAP",
              "value": "battle-unit_3"
            },
            {
              "type": "TAP",
              "value": "battle-unit_4"
            },
            {
              "type": "WAIT",
              "value": "200"
            },
            {
              "type": "REPEAT",
              "value": ""
            }
          ]
        },

        {
          "condition": {
            "is": "SCREEN",
            "value": "game-battle",
            "and": [
              {
                "not": "SCREEN",
                "value": "game-battle-auto_off"
              }
            ]
          },
          "actions": [
            {
              "type": "SET",
              "value": "0",
              "var": "_loops"
            }
          ]
        }
      ]
    }

  }
}